Topsis_package/__init__.py
Topsis_package/pro.py
topsis_3579-0.0.1.dist-info/LICENSE.txt
topsis_3579-0.0.1.dist-info/METADATA
topsis_3579-0.0.1.dist-info/WHEEL
topsis_3579-0.0.1.dist-info/top_level.txt
topsis_3579-0.0.1.dist-info/RECORD
