Metadata-Version: 2.1
Name: topsis-3579
Version: 0.0.1
Summary: Topsis package in Python
Home-page: 
Author: Tanishq Chopra
Author-email: tanishqtc1980@gmail.com
License: UNKNOWN
Platform: UNKNOWN
Classifier: Programming Language :: Python :: 3
Classifier: License :: OSI Approved :: MIT License
Classifier: Operating System :: OS Independent
Requires-Python: >=3.6
